KZTOOLS/AES.py
KZTOOLS/FakeHeaders.py
KZTOOLS/FakeUseragent.py
KZTOOLS/ImageRecognition.py
KZTOOLS/YoudaoTrans.py
KZTOOLS/__init__.py
KZTOOLS/demo.py
KZTOOLS/public.py
KZTOOLS-0.0.6.dist-info/METADATA
KZTOOLS-0.0.6.dist-info/WHEEL
KZTOOLS-0.0.6.dist-info/top_level.txt
KZTOOLS-0.0.6.dist-info/RECORD
