Metadata-Version: 2.1
Name: KZTOOLS
Version: 0.0.6
Summary: kz's tools
Home-page: https://github.com/Timiboy
Author: kz
Author-email: 767891749@qq.com
License: MIT
Platform: UNKNOWN
Classifier: License :: OSI Approved :: MIT License
Classifier: Programming Language :: Python
Classifier: Programming Language :: Python :: 3
Classifier: Programming Language :: Python :: 3.6
Classifier: Programming Language :: Python :: Implementation :: CPython
Classifier: Programming Language :: Python :: Implementation :: PyPy
Requires-Python: >=3.6.0
Requires-Dist: requests
Requires-Dist: lxml
Requires-Dist: pycryptodome
